crc_tool/__init__.py
crc_tool/main.py
crc_tool/input_file_handlers/__init__.py
crc_tool/input_file_handlers/elf_handler.py
crc_tool/input_file_handlers/txt_handler.py
crc_tool/util/__init__.py
crc_tool/util/consts.py
crc_tool/util/util.py
tests/__init__.py
tests/conftest.py
tests/generate_user_record/__init__.py
tests/generate_user_record/conftest.py
tests/generate_user_record/util/__init__.py
tests/generate_user_record/util/consts.py
tests/patch_image/__init__.py
tests/patch_image/integration/__init__.py
tests/patch_image/integration/test_whole_insertion.py
crc_tool-1.2.3.4.dist-info/LICENSE.txt
crc_tool-1.2.3.4.dist-info/METADATA
crc_tool-1.2.3.4.dist-info/WHEEL
crc_tool-1.2.3.4.dist-info/entry_points.txt
crc_tool-1.2.3.4.dist-info/top_level.txt
crc_tool-1.2.3.4.dist-info/RECORD
