Metadata-Version: 2.1
Name: crc-tool
Version: 1.2.3.4
Summary: UNKNOWN
Home-page: UNKNOWN
Author: Texas Instruments
Author-email: i.hovind@ti.com
License: UNKNOWN
Platform: UNKNOWN
Requires-Dist: cffi==1.15.1
Requires-Dist: lief==0.12.3
Requires-Dist: mypy
Requires-Dist: pyinstaller==5.6.2
Requires-Dist: pylint
Requires-Dist: pytest
Requires-Dist: pywin32-ctypes
